{
  "gitSyncId": "66a7a7644a0564113f6c39ed_b4d0660b-9d3b-41f4-bb66-acbcbab53fd3",
  "id": "Page2 Copy__$JSModule1_11$_JSModule1_1.myFun1",
  "isPublic": true,
  "moduleInstanceId": "Page2 Copy_JSModule1_11",
  "pluginId": "js-plugin",
  "pluginType": "JS",
  "rootModuleInstanceId": "Page2 Copy_JSModule1_11",
  "unpublishedAction": {
    "clientSideExecution": true,
    "collectionId": "Page2 Copy__$JSModule1_11$_JSModule1_1",
    "confirmBeforeExecute": false,
    "contextType": "PAGE",
    "datasource": {
      "isAutoGenerated": false,
      "name": "UNUSED_DATASOURCE",
      "pluginId": "js-plugin"
    },
    "executeOnLoad": true,
    "fullyQualifiedName": "_$JSModule1_11$_JSModule1_1.myFun1",
    "name": "myFun1",
    "pageId": "Page2 Copy",
    "userSetOnLoad": false
  }
}